<?xml version="1.0" ?> 
<cross-domain-policy>
  <allow-access-from domain="*.qq.com" /> 
  <allow-access-from domain="*.qzone.qq.com" /> 
  <allow-access-from domain="*.xiaoyou.qq.com" /> 
  <allow-access-from domain="*.cnc.qzone.qq.com" /> 
  <allow-access-from domain="*.edu.qzone.qq.com" /> 
  <allow-access-from domain="*.appimg.qq.com" /> 
  <allow-access-from domain="*.appimg1.qq.com" /> 
  <allow-access-from domain="*.appimg3.qq.com" /> 
  <allow-access-from domain="*.pengyou.com" /> 
</cross-domain-policy>